microgram/__init__.py
microgram/bot.py
microgram/chunking.py
microgram/helpers.py
microgram/text.py
microgram-1.0.1.dist-info/LICENSE
microgram-1.0.1.dist-info/METADATA
microgram-1.0.1.dist-info/WHEEL
microgram-1.0.1.dist-info/top_level.txt
microgram-1.0.1.dist-info/RECORD
