Metadata-Version: 2.1
Name: microgram
Version: 1.0.1
Summary: Simplest possible Python wrapper for Telegram Bot API
Classifier: Programming Language :: Python :: 3
Classifier: License :: OSI Approved :: MIT License
Classifier: Operating System :: OS Independent
License-File: LICENSE
Requires-Dist: httpx
Requires-Dist: python-json-logger
Requires-Dist: lark
